<?xml version="1.0" encoding="UTF-8"?>
<decorates>

    <decorate>
        <templet>m/decorate/tpstd.htm</templet>
        <path>x/bms/*</path>
    </decorate>

    <decorateReq>
        <templet>q/decorate/tpstd.htm</templet>
        <req>/login</req>
        <req>/xxx/req</req>
    </decorateReq>

    <!--<decorate>
        <templet>/temple2.htm</templet>
        <path>/xxx/xx/*</path>
        <path>/kkk2.htm</path>
        <path>/kkk3.htm</path>
    </decorate>-->
</decorates>